vkquick/__init__.py
vkquick/annotypes/__init__.py
vkquick/annotypes/base.py
vkquick/annotypes/callback_answer.py
vkquick/annotypes/chat_id.py
vkquick/annotypes/client_info.py
vkquick/annotypes/command_types.py
vkquick/annotypes/event.py
vkquick/annotypes/fwd_users.py
vkquick/annotypes/group_id.py
vkquick/annotypes/peer_id.py
vkquick/annotypes/replied_user.py
vkquick/annotypes/sender.py
vkquick/api.py
vkquick/bot.py
vkquick/console.py
vkquick/current.py
vkquick/exception.py
vkquick/lp.py
vkquick/reaction.py
vkquick/signal.py
vkquick/tools/__init__.py
vkquick/tools/button.py
vkquick/tools/doc.py
vkquick/tools/element.py
vkquick/tools/keyboard.py
vkquick/tools/message.py
vkquick/tools/photo.py
vkquick/tools/template.py
vkquick/tools/ui.py
vkquick/tools/uploader.py
vkquick/tools/user.py
vkquick/validators/__init__.py
vkquick/validators/action.py
vkquick/validators/base.py
vkquick/validators/chat_only.py
vkquick/validators/cmd.py
vkquick/validators/direct_only.py
vkquick-0.2.7.dist-info/entry_points.txt
vkquick-0.2.7.dist-info/LICENSE
vkquick-0.2.7.dist-info/WHEEL
vkquick-0.2.7.dist-info/METADATA
vkquick-0.2.7.dist-info/RECORD
