Metadata-Version: 2.1
Name: vkquick
Version: 0.2.7
Summary: Package for quick writing vk chat bots
Home-page: https://github.com/Rhinik/vkquick
License: MIT
Keywords: vk,async,bots,quick,api
Author: Kurbatov Yan
Author-email: deknowny@gmail.com
Requires-Python: >=3.8,<4.0
Classifier: Environment :: Console
Classifier: Framework :: AsyncIO
Classifier: Intended Audience :: Developers
Classifier: License :: OSI Approved :: MIT License
Classifier: Natural Language :: Russian
Classifier: Programming Language :: Python :: 3
Classifier: Programming Language :: Python :: 3.8
Classifier: Topic :: Documentation
Classifier: Topic :: Software Development :: Code Generators
Classifier: Topic :: Utilities
Classifier: Typing :: Typed
Requires-Dist: aiohttp (>=3.6.2,<4.0.0)
Requires-Dist: attrdict (>=2.0.1,<3.0.0)
Requires-Dist: click (>=7.1.2,<8.0.0)
Requires-Dist: colorama (>=0.4.3,<0.5.0)
Requires-Dist: pygments (>=2.6.1,<3.0.0)
Requires-Dist: requests (>=2.24.0,<3.0.0)
Requires-Dist: toml (>=0.10.1,<0.11.0)
Requires-Dist: watchdog (>=0.10.2,<0.11.0)
Project-URL: Documentation, https://vkquick.github.io
Project-URL: Help chat, https://vk.me/join/AJQ1dzLqwBeU7O0H_oJZYNjD
Project-URL: VK group, https://vk.com/vkquick
